ebot/__init__.py
ebot/ebotapi.py
ebot-0.1.0.dist-info/METADATA
ebot-0.1.0.dist-info/WHEEL
ebot-0.1.0.dist-info/top_level.txt
ebot-0.1.0.dist-info/RECORD
