Metadata-Version: 2.1
Name: ebot
Version: 0.1.0
Summary: A package with a variable API
Author: SunYingXin
Author-email: sunyingxin@baidu.com
Requires-Dist: requests
